QuICT/__init__.py
QuICT/algorithm/__init__.py
QuICT/algorithm/_algorithm.py
QuICT/algorithm/quantum_algorithm/__init__.py
QuICT/algorithm/quantum_algorithm/amplitude_estimate/QAE.py
QuICT/algorithm/quantum_algorithm/amplitude_estimate/__init__.py
QuICT/algorithm/quantum_algorithm/amplitude_estimate/utility.py
QuICT/algorithm/quantum_algorithm/amplitude_estimate/backend/FQAE.py
QuICT/algorithm/quantum_algorithm/amplitude_estimate/backend/__init__.py
QuICT/algorithm/quantum_algorithm/amplitude_estimate/backend/canonical_QAE.py
QuICT/algorithm/quantum_algorithm/amplitude_estimate/backend/max_likely_QAE.py
QuICT/algorithm/quantum_algorithm/cnf/__init__.py
QuICT/algorithm/quantum_algorithm/cnf/cnf.py
QuICT/algorithm/quantum_algorithm/grover/__init__.py
QuICT/algorithm/quantum_algorithm/grover/grover.py
QuICT/algorithm/quantum_algorithm/grover/partial_grover.py
QuICT/algorithm/quantum_algorithm/grover/search_with_prior_knowledge.py
QuICT/algorithm/quantum_algorithm/quantum_walk/__init__.py
QuICT/algorithm/quantum_algorithm/quantum_walk/graph.py
QuICT/algorithm/quantum_algorithm/quantum_walk/quantum_walk.py
QuICT/algorithm/quantum_algorithm/quantum_walk/quantum_walk_search.py
QuICT/algorithm/quantum_algorithm/shor/BEA.py
QuICT/algorithm/quantum_algorithm/shor/BEA_zip.py
QuICT/algorithm/quantum_algorithm/shor/HRS.py
QuICT/algorithm/quantum_algorithm/shor/HRS_zip.py
QuICT/algorithm/quantum_algorithm/shor/__init__.py
QuICT/algorithm/quantum_algorithm/shor/shor_factor.py
QuICT/algorithm/quantum_algorithm/shor/utility.py
QuICT/algorithm/tools/__init__.py
QuICT/algorithm/tools/drawer/__init__.py
QuICT/algorithm/tools/drawer/graph_drawer.py
QuICT/algorithm/weight_decision/__init__.py
QuICT/algorithm/weight_decision/weight_decision.py
QuICT/benchmark/__init__.py
QuICT/benchmark/benchmark.py
QuICT/core/__init__.py
QuICT/core/circuit/__init__.py
QuICT/core/circuit/circuit.py
QuICT/core/circuit/dag_circuit.py
QuICT/core/gate/__init__.py
QuICT/core/gate/composite_gate.py
quict-1.0.0.dist-info/LICENSE
quict-1.0.0.dist-info/METADATA
quict-1.0.0.dist-info/WHEEL
quict-1.0.0.dist-info/entry_points.txt
quict-1.0.0.dist-info/top_level.txt
quict-1.0.0.dist-info/RECORD
